Datasets/__init__.py
Datasets/BostonHousing/__init__.py
Datasets/BostonHousing/boston_housing.py
Datasets/FashionMNIST/__init__.py
Datasets/FashionMNIST/fashion_mnist.py
Datasets/Iris/__init__.py
Datasets/Iris/iris.py
Datasets/MNIST/__init__.py
Datasets/MNIST/mnist.py
DeeprAI_Datasets-0.0.2.dist-info/METADATA
DeeprAI_Datasets-0.0.2.dist-info/WHEEL
DeeprAI_Datasets-0.0.2.dist-info/top_level.txt
DeeprAI_Datasets-0.0.2.dist-info/RECORD
